turboseo/__init__.py
turboseo/analyzers/__init__.py
turboseo/analyzers/content_fetcher.py
turboseo/analyzers/content_length.py
turboseo/analyzers/keywords.py
turboseo/analyzers/readability.py
turboseo/analyzers/search_intent.py
turboseo/analyzers/seo_score.py
turboseo/analyzers/writing_standards.py
turboseo/cli/__init__.py
turboseo/cli/main.py
turboseo-0.2.0.dist-info/METADATA
turboseo-0.2.0.dist-info/WHEEL
turboseo-0.2.0.dist-info/entry_points.txt
turboseo-0.2.0.dist-info/licenses/LICENSE
turboseo-0.2.0.dist-info/RECORD
