Metadata-Version: 2.4
Name: turboseo
Version: 0.2.0
Summary: SEO content toolkit that writes human, not AI
Project-URL: Homepage, https://github.com/thijs/turboseo
Project-URL: Documentation, https://github.com/thijs/turboseo#readme
Project-URL: Repository, https://github.com/thijs/turboseo
Project-URL: Issues, https://github.com/thijs/turboseo/issues
Author: Thijs
License-Expression: MIT
License-File: LICENSE
Keywords: ai-detection,claude-code,content,marketing,seo,writing
Classifier: Development Status :: 3 - Alpha
Classifier: Environment :: Console
Classifier: Intended Audience :: Developers
Classifier: Intended Audience :: End Users/Desktop
Classifier: License :: OSI Approved :: MIT License
Classifier: Operating System :: OS Independent
Classifier: Programming Language :: Python :: 3
Classifier: Programming Language :: Python :: 3.10
Classifier: Programming Language :: Python :: 3.11
Classifier: Programming Language :: Python :: 3.12
Classifier: Topic :: Internet :: WWW/HTTP :: Site Management
Classifier: Topic :: Text Processing :: Linguistic
Requires-Python: >=3.10
Requires-Dist: click>=8.0.0
Requires-Dist: pydantic>=2.0.0
Requires-Dist: rich>=13.0.0
Requires-Dist: textstat>=0.7.0
Provides-Extra: dev
Requires-Dist: mypy>=1.0.0; extra == 'dev'
Requires-Dist: pytest-cov>=4.0.0; extra == 'dev'
Requires-Dist: pytest>=7.0.0; extra == 'dev'
Requires-Dist: ruff>=0.1.0; extra == 'dev'
